Metadata-Version: 1.1
Name: helga
Version: 1.7.13
Summary: A full-featured chat bot for Python 2.7 with plugin support
Home-page: https://github.com/shaunduncan/helga
Author: Shaun Duncan
Author-email: shaun.duncan@gmail.com
License: MIT/GPLv3
Keywords: helga bot irc xmpp jabber hipchat chat
Platform: UNKNOWN
Classifier: Development Status :: 5 - Production/Stable
Classifier: Topic :: Communications :: Chat :: Internet Relay Chat
Classifier: Framework :: Twisted
Classifier: License :: OSI Approved :: GNU General Public License v3 (GPLv3)
Classifier: License :: OSI Approved :: MIT License
Classifier: Operating System :: OS Independent
Classifier: Programming Language :: Python
Classifier: Programming Language :: Python :: 2
Classifier: Programming Language :: Python :: 2.6
Classifier: Programming Language :: Python :: 2.7
Classifier: Topic :: Software Development :: Libraries :: Python Modules
